toolsz/__init__.py
toolsz/dev.py
toolsz/freedom_function.py
toolsz/pyshark.py
toolsz-1.0.1.dist-info/METADATA
toolsz-1.0.1.dist-info/WHEEL
toolsz-1.0.1.dist-info/top_level.txt
toolsz-1.0.1.dist-info/RECORD
