Metadata-Version: 2.4
Name: toolsz
Version: 1.0.1
Summary: 负责工具
Requires-Python: >=3.10
Requires-Dist: dill>=0.3.9
Requires-Dist: llama-index>=0.12.30
Requires-Dist: lxml>=5.3.2
Requires-Dist: pyshark>=0.6
Requires-Dist: requests>=2.32.3
Requires-Dist: setproctitle>=1.3.5
Requires-Dist: setuptools>=78.1.0
Requires-Dist: toml>=0.10.2
